xodoo/__init__.py
xodoo/migration.py
xodoo/utils.py
xodoo-0.2.0.dist-info/LICENSE
xodoo-0.2.0.dist-info/METADATA
xodoo-0.2.0.dist-info/WHEEL
xodoo-0.2.0.dist-info/entry_points.txt
xodoo-0.2.0.dist-info/top_level.txt
xodoo-0.2.0.dist-info/RECORD
