Metadata-Version: 2.1
Name: xodoo
Version: 0.2.0
Summary: Odoo CLI Tools
Home-page: http://github.com/oerp-odoo/xodoo
Author: Andrius Laukavičius
Author-email: info@timefordev.com
License: LGPLv3+
Classifier: Intended Audience :: Developers
Classifier: License :: OSI Approved :: GNU Lesser General Public License v3 or later (LGPLv3+)
Classifier: Programming Language :: Python :: 3.9
Classifier: Programming Language :: Python :: 3.10
Classifier: Programming Language :: Python :: 3.11
Classifier: Framework :: Odoo
Requires-Python: >=3.9
License-File: LICENSE
Requires-Dist: click-odoo >=1.3.0
Requires-Dist: natsort >=8.4.0
